README.rst
setup.py
nose_mp_split.egg-info/PKG-INFO
nose_mp_split.egg-info/SOURCES.txt
nose_mp_split.egg-info/dependency_links.txt
nose_mp_split.egg-info/entry_points.txt
nose_mp_split.egg-info/requires.txt
nose_mp_split.egg-info/top_level.txt
nosempsplit/__init__.py
nosempsplit/plugin.py