Metadata-Version: 1.1
Name: nose-mp-split
Version: 0.0.1
Summary: an improved multiprocess plugin for nose
Home-page: https://github.com/pglass/nose-mp-split
Author: Paul Glass
Author-email: pnglass@gmail.com
License: UNKNOWN
Keywords: nose parallel multiprocess concurrency split
Platform: UNKNOWN
Classifier: Development Status :: 1 - Planning
Classifier: Environment :: Plugins
Classifier: Intended Audience :: Developers
Classifier: License :: OSI Approved :: MIT License
Classifier: Operating System :: OS Independent
Classifier: Programming Language :: Python :: 2.7
Classifier: Topic :: Software Development :: Testing
